{"header": [{"name": "obs", "title": "Origin", "size": 150, "sortable": true}, {"name": "ctp", "title": "Counterpart name", "size": 150, "sortable": true}, {"name": "ra", "title": "Right Ascension<br>[J2000]", "size": 50, "sortable": true}, {"name": "dec", "title": "Declination<br>[J2000]", "size": 50, "sortable": true}, {"name": "err", "title": "Positional error (90%)<br>[mas]", "size": 50, "sortable": true}], "data": [["fromID", "", 267.55308, -37.0519, 1000.0], ["HEAO", "1H1746-370", 267.5507, -37.054, 0.0], ["ARIEL3", "3A 1746-370", 267.5507, -37.054, 0.0], ["IGR", "4U 1746-370", 267.553, -37.052, 36000.001], ["FERMI", "4FGL J1750.3-3702", 267.5783, -37.0454, 72378.0], ["SAX", "4U 1746-370", 267.528, -37.075, 96000.001], ["initial", "", 267.5528, -37.0523, 0.0], ["Swift", "2SXPS J175012.4-370309", 267.55179, -37.0526, 2700.0], ["XMM", "4XMM J175012.7-370308", 267.55306, -37.0523, 474.739], ["Chandra", "2CXO J175012.7-370306", 267.55292, -37.0518, 709.906], ["Gaia", "Gaia DR3 4039968048223739392", 267.55288, -37.0524, 6.459]]}