{"header": [{"name": "obs", "title": "Origin", "size": 150, "sortable": true}, {"name": "ctp", "title": "Counterpart name", "size": 150, "sortable": true}, {"name": "ra", "title": "Right Ascension<br>[J2000]", "size": 50, "sortable": true}, {"name": "dec", "title": "Declination<br>[J2000]", "size": 50, "sortable": true}, {"name": "err", "title": "Positional error (90%)<br>[mas]", "size": 50, "sortable": true}], "data": [["fromID", "", 235.85, -56.4, 1400.0], ["IGR", "", 236.008, -56.712, 79200.003], ["2MASS", "", 235.84982, -56.4004, 80.0]]}