{"header": [{"name": "obs", "title": "Origin", "size": 150, "sortable": true}, {"name": "ctp", "title": "Counterpart name", "size": 150, "sortable": true}, {"name": "ra", "title": "Right Ascension<br>[J2000]", "size": 50, "sortable": true}, {"name": "dec", "title": "Declination<br>[J2000]", "size": 50, "sortable": true}, {"name": "err", "title": "Positional error (90%)<br>[mas]", "size": 50, "sortable": true}], "data": [["fromID", "", 282.51333, -0.9408, 1400.0], ["Swift", "2SXPS J185003.2-005623", 282.51373, -0.9398, 2600.0], ["initial", "", 282.537, -0.959, 0.0], ["2MASS", "2MASS J18500347-0056231", 282.51449, -0.9398, 90.0], ["Gaia", "Gaia DR3 4266054164622886144", 282.51451, -0.9398, 0.051]]}