{"header": [{"name": "obs", "title": "Origin", "size": 150, "sortable": true}, {"name": "ctp", "title": "Counterpart name", "size": 150, "sortable": true}, {"name": "ra", "title": "Right Ascension<br>[J2000]", "size": 50, "sortable": true}, {"name": "dec", "title": "Declination<br>[J2000]", "size": 50, "sortable": true}, {"name": "err", "title": "Positional error (90%)<br>[mas]", "size": 50, "sortable": true}], "data": [["fromID", "", 273.63167, -17.1547, 6000.0], ["HEAO", "1H1811-171", 273.6366, -17.1541, 0.0], ["ARIEL3", "3A 1811-171", 273.6366, -17.1541, 0.0], ["IGR", "GX 13+1", 273.631, -17.157, 18000.001], ["SAX", "GX 13+1", 273.625, -17.141, 96000.001], ["Swift", "2SXPS J181431.1-170922", 273.62965, -17.1564, 3500.0], ["initial", "", 273.6315, -17.1574, 0.0], ["2MASS", "2MASS J18143108-1709259", 273.62953, -17.1572, 60.0], ["Chandra", "2CXO J181431.0-170925", 273.62947, -17.1571, 1226.812]]}