{"header": [{"name": "obs", "title": "Origin", "size": 150, "sortable": true}, {"name": "ctp", "title": "Counterpart name", "size": 150, "sortable": true}, {"name": "ra", "title": "Right Ascension<br>[J2000]", "size": 50, "sortable": true}, {"name": "dec", "title": "Declination<br>[J2000]", "size": 50, "sortable": true}, {"name": "err", "title": "Positional error (90%)<br>[mas]", "size": 50, "sortable": true}], "data": [["fromID", "", 256.57667, -43.0481, 6000.0], ["IGR", "4U 1702-429", 256.564, -43.036, 19200.0], ["SAX", "4U 1702-429", 256.542, -43.054, 96000.001], ["initial", "", 256.5638, -43.0357, 0.0], ["2MASS", "2MASS J17061797-4302549", 256.57488, -43.0486, 60.0], ["Gaia", "Gaia DR3 5965460809643692544", 256.57519, -43.0485, 0.76]]}